MANIFEST.in
README.md
setup.py
django_thjodskra.egg-info/PKG-INFO
django_thjodskra.egg-info/SOURCES.txt
django_thjodskra.egg-info/dependency_links.txt
django_thjodskra.egg-info/top_level.txt
thjodskra/__init__.py
thjodskra/admin.py
thjodskra/models.py
thjodskra/searchable.py
thjodskra/tests.py
thjodskra/urls.py
thjodskra/utils.py
thjodskra/views.py
thjodskra/management/__init__.py
thjodskra/management/commands/__init__.py
thjodskra/management/commands/fetch_update.py
thjodskra/management/commands/import_people.py
thjodskra/management/commands/update_people.py
thjodskra/templates/thjodskra/person_list.html