Metadata-Version: 1.0
Name: django-thjodskra
Version: 0.411
Summary: django-thjodskra is a simple app for integrating the icelandic national registry into your django project
Home-page: https://github.com/ulfur/django-thjodskra
Author: Úlfur Kristjánsson
Author-email: ulfur@theawesometastic.com
License: UNKNOWN
Platform: UNKNOWN
